ncbiparser/README.md
ncbiparser/__inint__.py
ncbiparser/ncbi-parser.test.py
ncbiparser/ncbiparser.py
ncbiparser-1.1.0.data/data/README.md
ncbiparser-1.1.0.dist-info/METADATA
ncbiparser-1.1.0.dist-info/WHEEL
ncbiparser-1.1.0.dist-info/entry_points.txt
ncbiparser-1.1.0.dist-info/top_level.txt
ncbiparser-1.1.0.dist-info/RECORD
