Metadata-Version: 2.1
Name: ncbiparser
Version: 1.1.0
Summary: Search and fetch the Species Latin names, Accessory Number, Sequence Length, Division, Collection Country, Collection Date, Collected Worker, Identified Worker, and Reference information, etc. of the search records as tabular files.
Home-page: https://github.com/benben-miao/NCBI-Parser
Download-URL: https://pypi.org/project/ncbi-parser
Author: benben-miao
Author-email: benben.miao@outlook.com
Maintainer: benben-miao
Maintainer-email: benben.miao@outlook.com
License: MIT License
Keywords: CLI,Biology,NCBI,Parser
Platform: any
Classifier: Programming Language :: Python :: 3
Classifier: Operating System :: OS Independent
Requires-Dist: biopython
Requires-Dist: click
